{
  "annotations": {
    "list": [
      {
        "builtIn": 1,
        "datasource": "-- Grafana --",
        "enable": true,
        "hide": true,
        "iconColor": "rgba(0, 211, 255, 1)",
        "name": "Annotations & Alerts",
        "type": "dashboard"
      }
    ]
  },
  "editable": true,
  "gnetId": null,
  "graphTooltip": 0,
  "panels": [
    {
      "datasource": "$DS",
      "fieldConfig": {
        "defaults": {},
        "overrides": []
      },
      "gridPos": {
        "h": 8,
        "w": 24,
        "x": 0,
        "y": 0
      },
      "id": 0,
      "options": {
        "legend": {
          "displayMode": "list",
          "placement": "bottom"
        }
      },
      "targets": [
        {
          "expr": "tendermint_consensus_height{chain_id=\"$chain_id\", hostname=\"$hostname\"}",
          "refId": "A"
        }
      ],
      "title": "Block Height",
      "type": "timeseries"
    },
    {
      "datasource": "$DS",
      "fieldConfig": {
        "defaults": {},
        "overrides": []
      },
      "gridPos": {
        "h": 8,
        "w": 24,
        "x": 0,
        "y": 8
      },
      "id": 1,
      "options": {
        "legend": {
          "displayMode": "list",
          "placement": "bottom"
        }
      },
      "targets": [
        {
          "expr": "tendermint_mempool_size{chain_id=\"$chain_id\", hostname=\"$hostname\"}",
          "refId": "A"
        }
      ],
      "title": "Mempool Size",
      "type": "timeseries"
    },
    {
      "datasource": "$DS",
      "fieldConfig": {
        "defaults": {},
        "overrides": []
      },
      "gridPos": {
        "h": 8,
        "w": 24,
        "x": 0,
        "y": 16
      },
      "id": 2,
      "options": {
        "legend": {
          "displayMode": "list",
          "placement": "bottom"
        }
      },
      "targets": [
        {
          "expr": "tendermint_p2p_peers{chain_id=\"$chain_id\", hostname=\"$hostname\"}",
          "refId": "A"
        }
      ],
      "title": "Peers Connected",
      "type": "timeseries"
    },
    {
      "datasource": "$DS",
      "fieldConfig": {
        "defaults": {},
        "overrides": []
      },
      "gridPos": {
        "h": 8,
        "w": 24,
        "x": 0,
        "y": 24
      },
      "id": 3,
      "options": {
        "legend": {
          "displayMode": "list",
          "placement": "bottom"
        }
      },
      "targets": [
        {
          "expr": "tendermint_consensus_block_size_bytes{chain_id=\"$chain_id\", hostname=\"$hostname\"}",
          "refId": "A"
        }
      ],
      "title": "Block Size (bytes)",
      "type": "timeseries"
    },
    {
      "datasource": "$DS",
      "fieldConfig": {
        "defaults": {},
        "overrides": []
      },
      "gridPos": {
        "h": 8,
        "w": 24,
        "x": 0,
        "y": 32
      },
      "id": 4,
      "options": {
        "legend": {
          "displayMode": "list",
          "placement": "bottom"
        }
      },
      "targets": [
        {
          "expr": "rate(tendermint_state_block_processing_time_sum{chain_id=\"$chain_id\", hostname=\"$hostname\"}[5m]) / rate(tendermint_state_block_processing_time_count{chain_id=\"$chain_id\", hostname=\"$hostname\"}[5m])",
          "refId": "A"
        }
      ],
      "title": "Block Processing Time (s)",
      "type": "timeseries"
    },
    {
      "datasource": "$DS",
      "fieldConfig": {
        "defaults": {},
        "overrides": []
      },
      "gridPos": {
        "h": 8,
        "w": 24,
        "x": 0,
        "y": 40
      },
      "id": 5,
      "options": {
        "legend": {
          "displayMode": "list",
          "placement": "bottom"
        }
      },
      "targets": [
        {
          "expr": "tendermint_consensus_total_txs{chain_id=\"$chain_id\", hostname=\"$hostname\"}",
          "refId": "A"
        }
      ],
      "title": "Total Txs",
      "type": "timeseries"
    },
    {
      "datasource": "$DS",
      "fieldConfig": {
        "defaults": {},
        "overrides": []
      },
      "gridPos": {
        "h": 8,
        "w": 24,
        "x": 0,
        "y": 48
      },
      "id": 6,
      "options": {
        "legend": {
          "displayMode": "list",
          "placement": "bottom"
        }
      },
      "targets": [
        {
          "expr": "tendermint_consensus_validators{chain_id=\"$chain_id\", hostname=\"$hostname\"}",
          "refId": "A"
        }
      ],
      "title": "Validators",
      "type": "timeseries"
    },
    {
      "datasource": "$DS",
      "fieldConfig": {
        "defaults": {},
        "overrides": []
      },
      "gridPos": {
        "h": 8,
        "w": 24,
        "x": 0,
        "y": 56
      },
      "id": 7,
      "options": {
        "legend": {
          "displayMode": "list",
          "placement": "bottom"
        }
      },
      "targets": [
        {
          "expr": "tendermint_consensus_validators_power{chain_id=\"$chain_id\", hostname=\"$hostname\"}",
          "refId": "A"
        }
      ],
      "title": "Validators Power",
      "type": "timeseries"
    },
    {
      "datasource": "$DS",
      "fieldConfig": {
        "defaults": {},
        "overrides": []
      },
      "gridPos": {
        "h": 8,
        "w": 24,
        "x": 0,
        "y": 64
      },
      "id": 8,
      "options": {
        "legend": {
          "displayMode": "list",
          "placement": "bottom"
        }
      },
      "targets": [
        {
          "expr": "tendermint_consensus_byzantine_validators{chain_id=\"$chain_id\", hostname=\"$hostname\"}",
          "refId": "A"
        }
      ],
      "title": "Byzantine Validators Count",
      "type": "timeseries"
    },
    {
      "datasource": "$DS",
      "fieldConfig": {
        "defaults": {},
        "overrides": []
      },
      "gridPos": {
        "h": 8,
        "w": 24,
        "x": 0,
        "y": 72
      },
      "id": 9,
      "options": {
        "legend": {
          "displayMode": "list",
          "placement": "bottom"
        }
      },
      "targets": [
        {
          "expr": "tendermint_consensus_byzantine_validators_power{chain_id=\"$chain_id\", hostname=\"$hostname\"}",
          "refId": "A"
        }
      ],
      "title": "Byzantine Validators Power",
      "type": "timeseries"
    }
  ],
  "refresh": "10s",
  "schemaVersion": 27,
  "style": "dark",
  "tags": [
    "tendermint",
    "cosmos"
  ],
  "templating": {
    "list": [
      {
        "name": "DS",
        "type": "datasource",
        "query": "prometheus",
        "refresh": 1,
        "label": "Prometheus",
        "hide": 0
      },
      {
        "name": "chain_id",
        "type": "custom",
        "query": "dockerchain",
        "current": {
          "text": "dockerchain",
          "value": "dockerchain"
        },
        "label": "Chain ID"
      },
      {
        "name": "hostname",
        "type": "query",
        "datasource": "${DS}",
        "query": "label_values(tendermint_consensus_height, hostname)",
        "refresh": 2,
        "label": "Hostname"
      }
    ]
  },
  "time": {
    "from": "now-5m",
    "to": "now"
  },
  "timepicker": {},
  "timezone": "",
  "title": "Tendermint Dashboard (Auto-generated)",
  "version": 1
}